rektgbm/__init__.py
rektgbm/base.py
rektgbm/cli.py
rektgbm/dataset.py
rektgbm/encoder.py
rektgbm/engine.py
rektgbm/gbm.py
rektgbm/metric.py
rektgbm/objective.py
rektgbm/optimizer.py
rektgbm/param.py
rektgbm/task.py
rektgbm-0.1.6.dist-info/LICENSE
rektgbm-0.1.6.dist-info/METADATA
rektgbm-0.1.6.dist-info/WHEEL
rektgbm-0.1.6.dist-info/entry_points.txt
rektgbm-0.1.6.dist-info/RECORD
