Metadata-Version: 2.1
Name: rektgbm
Version: 0.1.6
Summary: No-brainer machine learning solution to achieve satisfactory performance
Home-page: https://github.com/RektPunk/RektGBM
License: MIT
Author: RektPunk
Author-email: rektpunk@gmail.com
Requires-Python: >=3.12,<4.0
Classifier: License :: OSI Approved :: MIT License
Classifier: Programming Language :: Python :: 3
Classifier: Programming Language :: Python :: 3.12
Classifier: Topic :: Software Development :: Build Tools
Classifier: Topic :: Software Development :: Libraries :: Python Modules
Requires-Dist: fastparquet (>=2024.5.0,<2025.0.0)
Requires-Dist: lightgbm (>=4.5.0,<5.0.0)
Requires-Dist: numpy (>=2.0.1,<3.0.0)
Requires-Dist: optuna (>=3.6.1,<4.0.0)
Requires-Dist: pandas (>=2.2.2,<3.0.0)
Requires-Dist: pyarrow (>=17.0.0,<18.0.0)
Requires-Dist: scikit-learn (>=1.5.1,<2.0.0)
Requires-Dist: typer (>=0.12.3,<0.13.0)
Requires-Dist: xgboost (>=2.1.1,<3.0.0)
Project-URL: Repository, https://github.com/RektPunk/RektGBM
